Makefile
collectd.d/ipa-data.conf
collectd.d/ipa.conf
collectd_ipa/__init__.py
collection.conf
types.db
collectd_ipa-1.0.0.dist-info/LICENSE
collectd_ipa-1.0.0.dist-info/WHEEL
collectd_ipa-1.0.0.dist-info/METADATA
collectd_ipa-1.0.0.dist-info/RECORD
