Metadata-Version: 2.1
Name: collectd-ipa
Version: 1.0.0
Summary: A CollectD plugin to get metrics from IPA
Home-page: https://github.com/fedora-infra/collectd-ipa
License: LGPL-3.0-or-later
Keywords: monitoring
Author: Fedora Infrastructure
Author-email: infrastructure@lists.fedoraproject.org
Requires-Python: >=3.6.2,<4.0.0
Classifier: Development Status :: 4 - Beta
Classifier: Intended Audience :: Developers
Classifier: License :: OSI Approved :: GNU Lesser General Public License v3 or later (LGPLv3+)
Classifier: Programming Language :: Python :: 3
Classifier: Programming Language :: Python :: 3.6
Classifier: Programming Language :: Python :: 3.7
Classifier: Programming Language :: Python :: 3.8
Classifier: Programming Language :: Python :: 3.9
Classifier: Topic :: Security
Classifier: Topic :: Software Development :: Libraries :: Python Modules
Requires-Dist: python-ldap (>=3.3.1,<4.0.0)
Project-URL: Repository, https://github.com/fedora-infra/collectd-ipa
